{"946870349406":{"type":"bo","bookName":"Lesson%209","subjectName":"Hatua%201","fName":"users/MS0vYW5kcm9pZF9hc3NldC93d3cvc2Nob29sL1Vzb21hamklMjBuYSUyMFVhbmRpc2hpL0hhdHVhJTIwMS9MZXNzb24lMjA5L2luZGV4Lmh0bWwtYW5hbHl0aWNzLTk0Njg3MDM0OTM4MA==.json"},"946870349408":{"type":"bo","bookName":"Lesson%209","subjectName":"Hatua%201","fName":"users/MS0vYW5kcm9pZF9hc3NldC93d3cvc2Nob29sL1Vzb21hamklMjBuYSUyMFVhbmRpc2hpL0hhdHVhJTIwMS9MZXNzb24lMjA5L2luZGV4Lmh0bWwtYW5hbHl0aWNzLTk0Njg3MDM0OTM4MA==.json"},"946870349521":{"type":"xl"},"946870350011":{"type":"xp","pageCount":21},"946870350338":{"type":"fl"},"946870350386":{"type":"st","linkname":"Page"},"946870350389":{"type":"ss","linkname":"Page"},"946870355575":{"type":"sf","linkname":"Page"},"946870357361":{"type":"ut","page":1,"pt":{"x":1210,"y":770}},"946870357434":{"type":"lt","linkname":"Link 2"},"946870357436":{"type":"st","linkname":"Link 2"},"946870357438":{"type":"ss","linkname":"Link 2"},"946870357441":{"type":"sf","linkname":"Link 2"},"946870357449":{"type":"sf","linkname":"Link 2"},"946870357899":{"type":"pt","page":2},"946870357911":{"type":"st","linkname":"Page"},"946870357914":{"type":"ss","linkname":"Page"},"946870371112":{"type":"sf","linkname":"Page"},"946870373060":{"type":"ut","page":2,"pt":{"x":735,"y":273}},"946870374485":{"type":"lt","linkname":"DropZone"},"946870374488":{"type":"st","linkname":"DropZone"},"946870374500":{"type":"ss","linkname":"DropZone"},"946870377265":{"type":"sf","linkname":"DropZone"},"946870393280":{"type":"ut","page":2,"pt":{"x":1249,"y":789}},"946870393327":{"type":"lt","linkname":"Link 1"},"946870393329":{"type":"st","linkname":"Link 1"},"946870393330":{"type":"ss","linkname":"Link 1"},"946870393332":{"type":"sf","linkname":"Link 1"},"946870393341":{"type":"sf","linkname":"Link 1"},"946870393801":{"type":"pt","page":3},"946870393810":{"type":"st","linkname":"Page"},"946870393813":{"type":"ss","linkname":"Page"},"946870400812":{"type":"ut","page":3,"pt":{"x":160,"y":411}},"946870401728":{"type":"ut","page":3,"pt":{"x":183,"y":438}},"946870405134":{"type":"sf","linkname":"Page"},"946870407971":{"type":"ut","page":3,"pt":{"x":202,"y":216}},"946870408074":{"type":"lt","linkname":"Workspace 1"},"946870409305":{"type":"ut","page":3,"pt":{"x":149,"y":226}},"946870410653":{"type":"lt","linkname":"Workspace 1"},"946870411250":{"type":"ut","page":3,"pt":{"x":214,"y":308}},"946870412948":{"type":"lt","linkname":"Workspace 1"},"946870414534":{"type":"ut","page":3,"pt":{"x":315,"y":326}},"946870417117":{"type":"lt","linkname":"Workspace 1"},"946870418058":{"type":"ut","page":3,"pt":{"x":439,"y":233}},"946870420637":{"type":"lt","linkname":"Workspace 1"},"946870421306":{"type":"ut","page":3,"pt":{"x":484,"y":298}},"946870423095":{"type":"lt","linkname":"Workspace 1"},"946870423592":{"type":"ut","page":3,"pt":{"x":581,"y":333}},"946870427124":{"type":"lt","linkname":"Workspace 1"},"946870427946":{"type":"ut","page":3,"pt":{"x":1212,"y":765}},"946870428022":{"type":"lt","linkname":"next page button"},"946870428033":{"type":"st","linkname":"next page button"},"946870428037":{"type":"ss","linkname":"next page button"},"946870428045":{"type":"sf","linkname":"next page button"},"946870428050":{"type":"sf","linkname":"next page button"},"946870428472":{"type":"pt","page":4},"946870428489":{"type":"st","linkname":"Page"},"946870428492":{"type":"ss","linkname":"Page"},"946870440384":{"type":"sf","linkname":"Page"},"946870444026":{"type":"ut","page":4,"pt":{"x":171,"y":216}},"946870446344":{"type":"lt","linkname":"Workspace 1"},"946870447236":{"type":"ut","page":4,"pt":{"x":249,"y":221}},"946870449835":{"type":"lt","linkname":"Workspace 1"},"946870450492":{"type":"ut","page":4,"pt":{"x":337,"y":329}},"946870452955":{"type":"lt","linkname":"Workspace 1"},"946870456012":{"type":"ut","page":4,"pt":{"x":420,"y":233}},"946870457863":{"type":"lt","linkname":"Workspace 1"},"946870458329":{"type":"ut","page":4,"pt":{"x":507,"y":234}},"946870460165":{"type":"lt","linkname":"Workspace 1"},"946870460641":{"type":"ut","page":4,"pt":{"x":602,"y":324}},"946870463068":{"type":"lt","linkname":"Workspace 1"},"946870464092":{"type":"ut","page":4,"pt":{"x":1221,"y":767}}}