{"1547480388285":{"type":"bo","bookName":"BasiAP","subjectName":"Top%20shelf","fName":"users/MS0vYW5kcm9pZF9hc3NldC93d3cvc2Nob29sL0Jvb2tzL1RvcCUyMHNoZWxmL0Jhc2lBUC9pbmRleC5odG1sLWFuYWx5dGljcy0xNTQ3NDgwMzg4MTY3.json"},"1547480388305":{"type":"bo","bookName":"BasiAP","subjectName":"Top%20shelf","fName":"users/MS0vYW5kcm9pZF9hc3NldC93d3cvc2Nob29sL0Jvb2tzL1RvcCUyMHNoZWxmL0Jhc2lBUC9pbmRleC5odG1sLWFuYWx5dGljcy0xNTQ3NDgwMzg4MTY3.json"},"1547480388391":{"type":"xl"},"1547480388831":{"type":"xp","pageCount":21},"1547480389069":{"type":"fl"},"1547480389104":{"type":"st","linkname":"Page"},"1547480389109":{"type":"ss","linkname":"Page"},"1547480401976":{"type":"sf","linkname":"Page"},"1547480403904":{"type":"ut","page":9,"pt":{"x":1210,"y":760}},"1547480404079":{"type":"lt","linkname":"next"},"1547480404081":{"type":"st","linkname":"next"},"1547480404084":{"type":"ss","linkname":"next"},"1547480404087":{"type":"sf","linkname":"next"},"1547480404096":{"type":"sf","linkname":"next"},"1547480404512":{"type":"pt","page":10},"1547480404533":{"type":"st","linkname":"Page"},"1547480404536":{"type":"ss","linkname":"Page"},"1547480413779":{"type":"sf","linkname":"Page"},"1547480415345":{"type":"ut","page":10,"pt":{"x":1214,"y":757}},"1547480415520":{"type":"lt","linkname":"next"},"1547480415522":{"type":"st","linkname":"next"},"1547480415536":{"type":"ss","linkname":"next"},"1547480415539":{"type":"sf","linkname":"next"},"1547480415546":{"type":"sf","linkname":"next"},"1547480415994":{"type":"pt","page":11},"1547480416004":{"type":"st","linkname":"Page"},"1547480416010":{"type":"ss","linkname":"Page"},"1547480429772":{"type":"sf","linkname":"Page"},"1547480431390":{"type":"ut","page":11,"pt":{"x":1213,"y":757}},"1547480431589":{"type":"lt","linkname":"next"},"1547480431591":{"type":"st","linkname":"next"},"1547480431600":{"type":"ss","linkname":"next"},"1547480431603":{"type":"sf","linkname":"next"},"1547480431609":{"type":"sf","linkname":"next"},"1547480432026":{"type":"pt","page":12},"1547480432042":{"type":"st","linkname":"Page"},"1547480432046":{"type":"ss","linkname":"Page"},"1547480438652":{"type":"sf","linkname":"Page"},"1547480440143":{"type":"ut","page":12,"pt":{"x":1202,"y":749}},"1547480440308":{"type":"lt","linkname":"next"},"1547480440309":{"type":"st","linkname":"next"},"1547480440314":{"type":"ss","linkname":"next"},"1547480440316":{"type":"sf","linkname":"next"},"1547480440321":{"type":"sf","linkname":"next"},"1547480440723":{"type":"pt","page":13},"1547480440732":{"type":"st","linkname":"Page"},"1547480440734":{"type":"ss","linkname":"Page"},"1547480450181":{"type":"sf","linkname":"Page"},"1547480451041":{"type":"ut","page":13,"pt":{"x":1201,"y":759}},"1547480451199":{"type":"lt","linkname":"next"},"1547480451200":{"type":"st","linkname":"next"},"1547480451222":{"type":"ss","linkname":"next"},"1547480451224":{"type":"sf","linkname":"next"},"1547480451244":{"type":"sf","linkname":"next"},"1547480451648":{"type":"pt","page":14},"1547480451676":{"type":"st","linkname":"Page"},"1547480451680":{"type":"ss","linkname":"Page"},"1547480459673":{"type":"sf","linkname":"Page"},"1547480461193":{"type":"ut","page":14,"pt":{"x":1215,"y":751}},"1547480461383":{"type":"lt","linkname":"next"},"1547480461384":{"type":"st","linkname":"next"},"1547480461421":{"type":"ss","linkname":"next"},"1547480461422":{"type":"sf","linkname":"next"},"1547480461448":{"type":"sf","linkname":"next"},"1547480461859":{"type":"pt","page":15},"1547480461894":{"type":"st","linkname":"Page"},"1547480461896":{"type":"ss","linkname":"Page"},"1547480473291":{"type":"sf","linkname":"Page"},"1547480474045":{"type":"ut","page":15,"pt":{"x":1205,"y":746}},"1547480474211":{"type":"lt","linkname":"next"},"1547480474212":{"type":"st","linkname":"next"},"1547480474244":{"type":"ss","linkname":"next"},"1547480474247":{"type":"sf","linkname":"next"},"1547480474276":{"type":"sf","linkname":"next"},"1547480474668":{"type":"pt","page":16},"1547480474706":{"type":"st","linkname":"Page"},"1547480474708":{"type":"ss","linkname":"Page"},"1547480491809":{"type":"sf","linkname":"Page"},"1547480496513":{"type":"ut","page":16,"pt":{"x":1236,"y":760}}}