{"947116905751":{"type":"book open","bookName":"Epic%20Quest","subjectName":"school","fName":"users/NC0vYW5kcm9pZF9hc3NldC93d3cvc2Nob29sL0VwaWMlMjBRdWVzdC92YXJpYWJsZS1FUV9HNF9CZWFkcy1FUV9HNF9CZWFkcy5odG1sLWFuYWx5dGljcy05NDcxMTY5MDU2OTM=.json"},"947116906310":{"type":"st"},"947116906311":{"type":"ss"},"947116912532":{"type":"sf"},"947116914603":{"type":"st"},"947116914604":{"type":"ss"},"947116915791":{"type":"sf"},"947116917302":{"type":"st"},"947116917303":{"type":"ss"},"947116918475":{"type":"sf"},"947116918493":{"type":"st"},"947116918498":{"type":"ss"},"947116931536":{"type":"sf"}}