{"946887834064":{"type":"bo","bookName":"Lesson%203","subjectName":"Hatua%204","fName":"users/Mi0vYW5kcm9pZF9hc3NldC93d3cvc2Nob29sL0hpc2FiYXRpL0hhdHVhJTIwNC9MZXNzb24lMjAzL2luZGV4Lmh0bWwtYW5hbHl0aWNzLTk0Njg4NzgzNDAzMg==.json"},"946887834079":{"type":"bo","bookName":"Lesson%203","subjectName":"Hatua%204","fName":"users/Mi0vYW5kcm9pZF9hc3NldC93d3cvc2Nob29sL0hpc2FiYXRpL0hhdHVhJTIwNC9MZXNzb24lMjAzL2luZGV4Lmh0bWwtYW5hbHl0aWNzLTk0Njg4NzgzNDAzMg==.json"},"946887834137":{"type":"xl"},"946887834385":{"type":"xp","pageCount":9},"946887834867":{"type":"fl"},"946887834904":{"type":"st","linkname":"Page"},"946887834911":{"type":"ss","linkname":"Page"},"946887836857":{"type":"ut","page":1,"pt":{"x":76,"y":732}},"946887838866":{"type":"ut","page":1,"pt":{"x":70,"y":768}},"946887839268":{"type":"ut","page":1,"pt":{"x":56,"y":741}},"946887839631":{"type":"ut","page":1,"pt":{"x":78,"y":756}},"946887882386":{"type":"sf","linkname":"Page"},"946887886422":{"type":"ut","page":1,"pt":{"x":1170,"y":406}},"946887887701":{"type":"ut","page":1,"pt":{"x":1175,"y":412}},"946887888330":{"type":"ut","page":1,"pt":{"x":1218,"y":754}},"946887888448":{"type":"lt","linkname":"NextPage"},"946887888450":{"type":"st","linkname":"NextPage"},"946887888453":{"type":"ss","linkname":"NextPage"},"946887888457":{"type":"sf","linkname":"NextPage"},"946887888467":{"type":"sf","linkname":"NextPage"},"946887888851":{"type":"pt","page":2},"946887888863":{"type":"st","linkname":"Page"},"946887888865":{"type":"ss","linkname":"Page"},"946887902750":{"type":"sf","linkname":"Page"},"946887904415":{"type":"ut","page":2,"pt":{"x":973,"y":442}},"946887905626":{"type":"ut","page":2,"pt":{"x":942,"y":445}},"946887906641":{"type":"ut","page":2,"pt":{"x":1195,"y":744}},"946887906716":{"type":"lt","linkname":"NextPage"},"946887906717":{"type":"st","linkname":"NextPage"},"946887906719":{"type":"ss","linkname":"NextPage"},"946887906720":{"type":"sf","linkname":"NextPage"},"946887906730":{"type":"sf","linkname":"NextPage"},"946887907141":{"type":"pt","page":3},"946887907152":{"type":"st","linkname":"Page"},"946887907155":{"type":"ss","linkname":"Page"},"946887923799":{"type":"sf","linkname":"Page"},"946887930038":{"type":"ut","page":3,"pt":{"x":949,"y":244}},"946887930835":{"type":"ut","page":3,"pt":{"x":894,"y":227}},"946887931534":{"type":"ut","page":3,"pt":{"x":964,"y":245}},"946887932292":{"type":"ut","page":3,"pt":{"x":1188,"y":91}},"946887933201":{"type":"ut","page":3,"pt":{"x":1207,"y":333}},"946887933748":{"type":"ut","page":3,"pt":{"x":1187,"y":313}},"946887938814":{"type":"ut","page":3,"pt":{"x":1179,"y":303}},"946887940900":{"type":"ut","page":3,"pt":{"x":1183,"y":335}},"946887942568":{"type":"ut","page":3,"pt":{"x":1187,"y":336}},"946887943292":{"type":"ut","page":3,"pt":{"x":87,"y":771}},"946887943470":{"type":"lt","linkname":"ResetPage"},"946887943471":{"type":"st","linkname":"ResetPage"},"946887943473":{"type":"ss","linkname":"ResetPage"},"946887943478":{"type":"sf","linkname":"ResetPage"},"946887943882":{"type":"ut","page":3,"pt":{"x":53,"y":725}},"946887944025":{"type":"lt","linkname":"ResetPage"},"946887944026":{"type":"st","linkname":"ResetPage"},"946887944028":{"type":"ss","linkname":"ResetPage"},"946887944033":{"type":"sf","linkname":"ResetPage"},"946887944471":{"type":"ut","page":3,"pt":{"x":70,"y":718}},"946887944580":{"type":"lt","linkname":"ResetPage"},"946887944582":{"type":"st","linkname":"ResetPage"},"946887944583":{"type":"ss","linkname":"ResetPage"},"946887944589":{"type":"sf","linkname":"ResetPage"}}