{"946789773140":{"type":"bo","bookName":"Game%203%20dif%203","subjectName":"Hatua%201","fName":"users/Mi0vYW5kcm9pZF9hc3NldC93d3cvc2Nob29sL0hpc2FiYXRpL0hhdHVhJTIwMS9HYW1lJTIwMyUyMGRpZiUyMDMvaW5kZXguaHRtbC1hbmFseXRpY3MtOTQ2Nzg5NzczMDk4.json"},"946789773151":{"type":"bo","bookName":"Game%203%20dif%203","subjectName":"Hatua%201","fName":"users/Mi0vYW5kcm9pZF9hc3NldC93d3cvc2Nob29sL0hpc2FiYXRpL0hhdHVhJTIwMS9HYW1lJTIwMyUyMGRpZiUyMDMvaW5kZXguaHRtbC1hbmFseXRpY3MtOTQ2Nzg5NzczMDk4.json"},"946789773291":{"type":"xl"},"946789773878":{"type":"xp","pageCount":9},"946789774938":{"type":"fl"},"946789774973":{"type":"st","linkname":"Page"},"946789774979":{"type":"ss","linkname":"Page"},"946789777186":{"type":"ut","page":1,"pt":{"x":33,"y":118}},"946789781090":{"type":"ut","page":1,"pt":{"x":823,"y":46}},"946789787332":{"type":"ut","page":1,"pt":{"x":791,"y":67}},"946789787669":{"type":"ut","page":1,"pt":{"x":746,"y":54}},"946789787870":{"type":"ut","page":1,"pt":{"x":746,"y":64}},"946789788761":{"type":"ut","page":1,"pt":{"x":770,"y":150}},"946789789197":{"type":"ut","page":1,"pt":{"x":721,"y":180}},"946789789802":{"type":"ut","page":1,"pt":{"x":664,"y":286}},"946789790029":{"type":"ut","page":1,"pt":{"x":677,"y":308}},"946789790239":{"type":"ut","page":1,"pt":{"x":656,"y":314}},"946789790685":{"type":"ut","page":1,"pt":{"x":653,"y":332}},"946789790928":{"type":"ut","page":1,"pt":{"x":642,"y":321}},"946789791096":{"type":"ut","page":1,"pt":{"x":681,"y":336}},"946789798669":{"type":"sf","linkname":"Page"},"946789804626":{"type":"ut","page":1,"pt":{"x":156,"y":717}},"946789804695":{"type":"lt","linkname":"Recipe book"},"946789804698":{"type":"st","linkname":"Recipe book"},"946789804704":{"type":"ss","linkname":"Recipe book"},"946789806003":{"type":"sf","linkname":"Recipe book"},"946789807291":{"type":"ut","page":1,"pt":{"x":805,"y":457}},"946789807354":{"type":"lt","linkname":"Link 2"},"946789807355":{"type":"st","linkname":"Link 2"},"946789807357":{"type":"ss","linkname":"Link 2"},"946789808632":{"type":"sf","linkname":"Link 2"},"946789809042":{"type":"ut","page":1,"pt":{"x":1188,"y":430}},"946789809125":{"type":"lt","linkname":"Rbook right_cup"},"946789809126":{"type":"st","linkname":"Rbook right_cup"},"946789809128":{"type":"ss","linkname":"Rbook right_cup"},"946789810487":{"type":"sf","linkname":"Rbook right_cup"},"946789811134":{"type":"ut","page":1,"pt":{"x":827,"y":440}},"946789811208":{"type":"lt","linkname":"Link 2"},"946789811209":{"type":"st","linkname":"Link 2"},"946789811212":{"type":"ss","linkname":"Link 2"},"946789812485":{"type":"sf","linkname":"Link 2"},"946789812754":{"type":"ut","page":1,"pt":{"x":1252,"y":455}},"946789813728":{"type":"ut","page":1,"pt":{"x":1251,"y":480}},"946789814711":{"type":"ut","page":1,"pt":{"x":1238,"y":444}},"946789814752":{"type":"lt","linkname":"Rbook right_soup"},"946789814754":{"type":"st","linkname":"Rbook right_soup"},"946789814757":{"type":"ss","linkname":"Rbook right_soup"},"946789816080":{"type":"sf","linkname":"Rbook right_soup"},"946789816626":{"type":"ut","page":1,"pt":{"x":872,"y":470}},"946789816692":{"type":"lt","linkname":"Link 2"},"946789816693":{"type":"st","linkname":"Link 2"},"946789816695":{"type":"ss","linkname":"Link 2"},"946789817961":{"type":"sf","linkname":"Link 2"},"946789818188":{"type":"ut","page":1,"pt":{"x":1219,"y":419}},"946789818273":{"type":"lt","linkname":"Rbook right_pie"},"946789818274":{"type":"st","linkname":"Rbook right_pie"},"946789818277":{"type":"ss","linkname":"Rbook right_pie"},"946789819612":{"type":"sf","linkname":"Rbook right_pie"},"946789820112":{"type":"ut","page":1,"pt":{"x":839,"y":413}},"946789820188":{"type":"lt","linkname":"Link 2"},"946789820190":{"type":"st","linkname":"Link 2"},"946789820192":{"type":"ss","linkname":"Link 2"},"946789821495":{"type":"sf","linkname":"Link 2"},"946789821750":{"type":"ut","page":1,"pt":{"x":1254,"y":443}},"946789821818":{"type":"lt","linkname":"Rbook right_cup"},"946789821819":{"type":"st","linkname":"Rbook right_cup"},"946789821821":{"type":"ss","linkname":"Rbook right_cup"},"946789823150":{"type":"sf","linkname":"Rbook right_cup"},"946789823480":{"type":"ut","page":1,"pt":{"x":829,"y":406}},"946789823556":{"type":"lt","linkname":"Link 2"},"946789823558":{"type":"st","linkname":"Link 2"},"946789823559":{"type":"ss","linkname":"Link 2"},"946789824858":{"type":"sf","linkname":"Link 2"},"946789824958":{"type":"ut","page":1,"pt":{"x":1220,"y":439}},"946789825042":{"type":"lt","linkname":"Rbook right_soup"},"946789825043":{"type":"st","linkname":"Rbook right_soup"},"946789825045":{"type":"ss","linkname":"Rbook right_soup"},"946789826376":{"type":"sf","linkname":"Rbook right_soup"},"946789826756":{"type":"ut","page":1,"pt":{"x":890,"y":448}},"946789826824":{"type":"lt","linkname":"Link 2"},"946789826825":{"type":"st","linkname":"Link 2"},"946789826827":{"type":"ss","linkname":"Link 2"},"946789828115":{"type":"sf","linkname":"Link 2"},"946789828161":{"type":"ut","page":1,"pt":{"x":1186,"y":470}},"946789828268":{"type":"lt","linkname":"Rbook right_pie"},"946789828270":{"type":"st","linkname":"Rbook right_pie"},"946789828271":{"type":"ss","linkname":"Rbook right_pie"},"946789829595":{"type":"sf","linkname":"Rbook right_pie"},"946789830158":{"type":"ut","page":1,"pt":{"x":1200,"y":58}},"946789830199":{"type":"lt","linkname":"RBook Exit"},"946789830200":{"type":"st","linkname":"RBook Exit"},"946789830202":{"type":"ss","linkname":"RBook Exit"},"946789831495":{"type":"sf","linkname":"RBook Exit"},"946789832334":{"type":"ut","page":1,"pt":{"x":28,"y":54}},"946789832582":{"type":"lt","linkname":"DROP_right_1"},"946789832585":{"type":"st","linkname":"DROP_right_1"},"946789832596":{"type":"ss","linkname":"DROP_right_1"},"946789834343":{"type":"ut","page":1,"pt":{"x":111,"y":87}},"946789834708":{"type":"sf","linkname":"DROP_right_1"},"946789835047":{"type":"ut","page":1,"pt":{"x":143,"y":101}},"946789835395":{"type":"lt","linkname":"WRONG_2"},"946789835397":{"type":"st","linkname":"WRONG_2"},"946789835408":{"type":"ss","linkname":"WRONG_2"},"946789836955":{"type":"ut","page":1,"pt":{"x":139,"y":75}},"946789837511":{"type":"st","linkname":false},"946789837515":{"type":"ss","linkname":false},"946789837524":{"type":"sf","linkname":"WRONG_2"},"946789837636":{"type":"ut","page":1,"pt":{"x":196,"y":83}},"946789837952":{"type":"lt","linkname":"WRONG_1"},"946789837954":{"type":"st","linkname":"WRONG_1"},"946789837965":{"type":"ss","linkname":"WRONG_1"},"946789839437":{"type":"ut","page":1,"pt":{"x":26,"y":248}},"946789840089":{"type":"ut","page":1,"pt":{"x":50,"y":271}},"946789840173":{"type":"sf","linkname":false},"946789840175":{"type":"st","linkname":false},"946789840179":{"type":"ss","linkname":false},"946789840666":{"type":"ut","page":1,"pt":{"x":52,"y":267}},"946789841954":{"type":"ut","page":1,"pt":{"x":18,"y":255}},"946789842590":{"type":"lt","linkname":"DROP_right_2"},"946789842592":{"type":"st","linkname":"DROP_right_2"},"946789842603":{"type":"ss","linkname":"DROP_right_2"},"946789843888":{"type":"ut","page":1,"pt":{"x":155,"y":262}},"946789844299":{"type":"ut","page":1,"pt":{"x":113,"y":295}},"946789844780":{"type":"sf","linkname":"DROP_right_2"},"946789844815":{"type":"ut","page":1,"pt":{"x":124,"y":270}},"946789845191":{"type":"lt","linkname":"WRONG_5"},"946789845195":{"type":"st","linkname":"WRONG_5"},"946789845204":{"type":"ss","linkname":"WRONG_5"},"946789845267":{"type":"ut","page":1,"pt":{"x":300,"y":212}},"946789847266":{"type":"ut","page":1,"pt":{"x":186,"y":279}},"946789847756":{"type":"sf","linkname":false},"946789847758":{"type":"st","linkname":false},"946789847762":{"type":"ss","linkname":false},"946789847900":{"type":"ut","page":1,"pt":{"x":206,"y":344}},"946789848534":{"type":"ut","page":1,"pt":{"x":205,"y":386}},"946789849028":{"type":"lt","linkname":"DROP_right_3"},"946789849031":{"type":"st","linkname":"DROP_right_3"},"946789849040":{"type":"ss","linkname":"DROP_right_3"},"946789850536":{"type":"ut","page":1,"pt":{"x":178,"y":260}},"946789850888":{"type":"ut","page":1,"pt":{"x":198,"y":307}},"946789851163":{"type":"sf","linkname":"DROP_right_3"},"946789851166":{"type":"st","linkname":"logic"},"946789851170":{"type":"ss","linkname":"logic"},"946789851325":{"type":"ut","page":1,"pt":{"x":130,"y":423}},"946789852023":{"type":"ut","page":1,"pt":{"x":103,"y":405}},"946789852638":{"type":"ut","page":1,"pt":{"x":204,"y":275}},"946789854082":{"type":"ut","page":1,"pt":{"x":158,"y":347}},"946789854552":{"type":"ut","page":1,"pt":{"x":122,"y":465}},"946789855073":{"type":"ut","page":1,"pt":{"x":96,"y":424}},"946789857696":{"type":"ut","page":1,"pt":{"x":544,"y":401}},"946789859192":{"type":"ut","page":1,"pt":{"x":550,"y":362}},"946789860055":{"type":"ut","page":1,"pt":{"x":834,"y":422}},"946789860829":{"type":"ut","page":1,"pt":{"x":820,"y":420}},"946789861416":{"type":"ut","page":1,"pt":{"x":837,"y":403}},"946789861803":{"type":"ut","page":1,"pt":{"x":814,"y":421}},"946789862231":{"type":"ut","page":1,"pt":{"x":806,"y":445}},"946789862626":{"type":"ut","page":1,"pt":{"x":191,"y":701}},"946789863382":{"type":"ut","page":1,"pt":{"x":800,"y":414}},"946789865510":{"type":"ut","page":1,"pt":{"x":438,"y":110}},"946789865861":{"type":"ut","page":1,"pt":{"x":851,"y":371}},"946789866205":{"type":"ut","page":1,"pt":{"x":824,"y":451}},"946789866633":{"type":"ut","page":1,"pt":{"x":598,"y":425}},"946789867079":{"type":"ut","page":1,"pt":{"x":857,"y":453}},"946789867465":{"type":"ut","page":1,"pt":{"x":807,"y":411}},"946789868078":{"type":"ut","page":1,"pt":{"x":226,"y":260}},"946789868988":{"type":"ut","page":1,"pt":{"x":202,"y":234}},"946789869826":{"type":"ut","page":1,"pt":{"x":313,"y":449}},"946789870162":{"type":"ut","page":1,"pt":{"x":308,"y":396}},"946789870666":{"type":"ut","page":1,"pt":{"x":307,"y":556}},"946789871111":{"type":"ut","page":1,"pt":{"x":297,"y":391}},"946789871724":{"type":"ut","page":1,"pt":{"x":315,"y":237}},"946789872203":{"type":"ut","page":1,"pt":{"x":293,"y":69}},"946789872919":{"type":"ut","page":1,"pt":{"x":628,"y":61}},"946789873413":{"type":"ut","page":1,"pt":{"x":640,"y":197}},"946789873875":{"type":"ut","page":1,"pt":{"x":1095,"y":418}},"946789874211":{"type":"ut","page":1,"pt":{"x":1131,"y":444}},"946789875009":{"type":"ut","page":1,"pt":{"x":954,"y":550}},"946789875673":{"type":"ut","page":1,"pt":{"x":966,"y":572}}}