{"947567146042":{"type":"book open","bookName":"Epic%20Quest","subjectName":"school","fName":"users/MS0vYW5kcm9pZF9hc3NldC93d3cvc2Nob29sL0VwaWMlMjBRdWVzdC92YXJpYWJsZS1FUV9WSUxMX1VQREFURS1FUV9WaWxsYWdlLmh0bWwtYW5hbHl0aWNzLTk0NzU2NzE0NTk3Ng==.json"},"947567147469":{"type":"st"},"947567147471":{"type":"ss"},"947567147496":{"type":"sf"},"947567155248":{"type":"st"},"947567155249":{"type":"ss"},"947567155788":{"type":"sf"},"947567159634":{"type":"st"},"947567159635":{"type":"ss"},"947567160160":{"type":"sf"},"947567160732":{"type":"st"},"947567160733":{"type":"ss"},"947567161162":{"type":"sf"},"947567167381":{"type":"st"},"947567167383":{"type":"ss"},"947567167904":{"type":"sf"},"947567172721":{"type":"st"},"947567172722":{"type":"ss"},"947567173237":{"type":"sf"},"947567176057":{"type":"st"},"947567176058":{"type":"ss"},"947567176565":{"type":"sf"},"947567185685":{"type":"st"},"947567185687":{"type":"ss"},"947567195088":{"type":"sf"},"947568423235":{"type":"bc"}}