{"RT_log_version":"1.0.1","RT_log_data":[{"type":"LOG_DATA","tutor":"story.pic.hear::story_25","class":"INFO","tag":"PERFORMANCE_TAG","time":"1548327821299","data":{"timestamp":" 1548327821298"," userId":" 5B12002999"," sessionId":" 5B12002999_20190124_140327"," gameId":" 099d54f0-2bc1-4190-a3be-3f81c960c407"," language":" LANG_SW"," tutorName":" bubble_pop"," tutorId":" bpop.ltr.uc_J..J.all.rand.all.stat.noShow.46"," matrixName":" literacy"," levelName":" null"," taskName":" BACKBUTTON"," problemName":" BPOP_J_M-N-J"," problemNumber":" 4"," substepNumber":" -1"," substepProblem":" 0"," attemptNumber":" 1"," expectedAnswer":" null"," userResponse":" null"," correctness":" null"," feedbackType":" null"," totalProblemsCount":" 0"," promotionMode":" PROMOTION"," scaffolding":" null"}},
{"type":"LOG_DATA","tutor":"bpop.ltr.uc:K..K.all.rand.all.stat.show.47","class":"INFO","tag":"PERFORMANCE_TAG","time":"1548327831438","data":{"timestamp":" 1548327831438"," userId":" 5B12002999"," sessionId":" 5B12002999_20190124_140327"," gameId":" 0c16d53e-b4f7-4771-a5c1-4c31f0ce8671"," language":" LANG_SW"," tutorName":" bubble_pop"," tutorId":" bpop.ltr.uc_K..K.all.rand.all.stat.show.47"," matrixName":" literacy"," levelName":" null"," taskName":" null"," problemName":" BPOP_K_D-K-R"," problemNumber":" 1"," substepNumber":" 1"," substepProblem":" 1"," attemptNumber":" 1"," expectedAnswer":" K"," userResponse":" K"," correctness":" CORRECT"," feedbackType":" null"," totalProblemsCount":" 10"," promotionMode":" PROMOTION"," scaffolding":" null"}},
{"type":"LOG_DATA","tutor":"bpop.ltr.uc:K..K.all.rand.all.stat.show.47","class":"INFO","tag":"PERFORMANCE_TAG","time":"1548327834645","data":{"timestamp":" 1548327834644"," userId":" 5B12002999"," sessionId":" 5B12002999_20190124_140327"," gameId":" 0c16d53e-b4f7-4771-a5c1-4c31f0ce8671"," language":" LANG_SW"," tutorName":" bubble_pop"," tutorId":" bpop.ltr.uc_K..K.all.rand.all.stat.show.47"," matrixName":" literacy"," levelName":" null"," taskName":" null"," problemName":" BPOP_K_V-J-K"," problemNumber":" 2"," substepNumber":" 1"," substepProblem":" 1"," attemptNumber":" 1"," expectedAnswer":" K"," userResponse":" K"," correctness":" CORRECT"," feedbackType":" null"," totalProblemsCount":" 10"," promotionMode":" PROMOTION"," scaffolding":" null"}},
{"type":"LOG_DATA","tutor":"bpop.ltr.uc:K..K.all.rand.all.stat.show.47","class":"INFO","tag":"PERFORMANCE_TAG","time":"1548327837919","data":{"timestamp":" 1548327837918"," userId":" 5B12002999"," sessionId":" 5B12002999_20190124_140327"," gameId":" 0c16d53e-b4f7-4771-a5c1-4c31f0ce8671"," language":" LANG_SW"," tutorName":" bubble_pop"," tutorId":" bpop.ltr.uc_K..K.all.rand.all.stat.show.47"," matrixName":" literacy"," levelName":" null"," taskName":" null"," problemName":" BPOP_K_Z-K-O"," problemNumber":" 3"," substepNumber":" 1"," substepProblem":" 1"," attemptNumber":" 1"," expectedAnswer":" K"," userResponse":" K"," correctness":" CORRECT"," feedbackType":" null"," totalProblemsCount":" 10"," promotionMode":" PROMOTION"," scaffolding":" null"}},
{"type":"LOG_DATA","tutor":"bpop.ltr.uc:K..K.all.rand.all.stat.show.47","class":"INFO","tag":"PERFORMANCE_TAG","time":"1548327840922","data":{"timestamp":" 1548327840922"," userId":" 5B12002999"," sessionId":" 5B12002999_20190124_140327"," gameId":" 0c16d53e-b4f7-4771-a5c1-4c31f0ce8671"," language":" LANG_SW"," tutorName":" bubble_pop"," tutorId":" bpop.ltr.uc_K..K.all.rand.all.stat.show.47"," matrixName":" literacy"," levelName":" null"," taskName":" null"," problemName":" BPOP_K_K-V-CH"," problemNumber":" 4"," substepNumber":" 1"," substepProblem":" 1"," attemptNumber":" 1"," expectedAnswer":" K"," userResponse":" K"," correctness":" CORRECT"," feedbackType":" null"," totalProblemsCount":" 10"," promotionMode":" PROMOTION"," scaffolding":" null"}},
{"type":"LOG_DATA","tutor":"bpop.ltr.uc:K..K.all.rand.all.stat.show.47","class":"INFO","tag":"PERFORMANCE_TAG","time":"1548327850227","data":{"timestamp":" 1548327850227"," userId":" 5B12002999"," sessionId":" 5B12002999_20190124_140327"," gameId":" 0c16d53e-b4f7-4771-a5c1-4c31f0ce8671"," language":" LANG_SW"," tutorName":" bubble_pop"," tutorId":" bpop.ltr.uc_K..K.all.rand.all.stat.show.47"," matrixName":" literacy"," levelName":" null"," taskName":" null"," problemName":" BPOP_K_V-E-K"," problemNumber":" 5"," substepNumber":" 1"," substepProblem":" 1"," attemptNumber":" 1"," expectedAnswer":" K"," userResponse":" K"," correctness":" CORRECT"," feedbackType":" null"," totalProblemsCount":" 10"," promotionMode":" PROMOTION"," scaffolding":" null"}},
{"type":"LOG_DATA","tutor":"bpop.ltr.uc:K..K.all.rand.all.stat.show.47","class":"INFO","tag":"PERFORMANCE_TAG","time":"1548327859987","data":{"timestamp":" 1548327859986"," userId":" 5B12002999"," sessionId":" 5B12002999_20190124_140327"," gameId":" 0c16d53e-b4f7-4771-a5c1-4c31f0ce8671"," language":" LANG_SW"," tutorName":" bubble_pop"," tutorId":" bpop.ltr.uc_K..K.all.rand.all.stat.show.47"," matrixName":" literacy"," levelName":" null"," taskName":" null"," problemName":" BPOP_K_J-Y-K"," problemNumber":" 6"," substepNumber":" 1"," substepProblem":" 1"," attemptNumber":" 1"," expectedAnswer":" K"," userResponse":" K"," correctness":" CORRECT"," feedbackType":" null"," totalProblemsCount":" 10"," promotionMode":" PROMOTION"," scaffolding":" null"}},
{"type":"LOG_DATA","tutor":"bpop.ltr.uc:K..K.all.rand.all.stat.show.47","class":"INFO","tag":"PERFORMANCE_TAG","time":"1548327865056","data":{"timestamp":" 1548327865056"," userId":" 5B12002999"," sessionId":" 5B12002999_20190124_140327"," gameId":" 0c16d53e-b4f7-4771-a5c1-4c31f0ce8671"," language":" LANG_SW"," tutorName":" bubble_pop"," tutorId":" bpop.ltr.uc_K..K.all.rand.all.stat.show.47"," matrixName":" literacy"," levelName":" null"," taskName":" null"," problemName":" BPOP_K_J-K-R"," problemNumber":" 7"," substepNumber":" 1"," substepProblem":" 1"," attemptNumber":" 1"," expectedAnswer":" K"," userResponse":" K"," correctness":" CORRECT"," feedbackType":" null"," totalProblemsCount":" 10"," promotionMode":" PROMOTION"," scaffolding":" null"}},
{"type":"LOG_DATA","tutor":"bpop.ltr.uc:K..K.all.rand.all.stat.show.47","class":"INFO","tag":"PERFORMANCE_TAG","time":"1548327869038","data":{"timestamp":" 1548327869037"," userId":" 5B12002999"," sessionId":" 5B12002999_20190124_140327"," gameId":" 0c16d53e-b4f7-4771-a5c1-4c31f0ce8671"," language":" LANG_SW"," tutorName":" bubble_pop"," tutorId":" bpop.ltr.uc_K..K.all.rand.all.stat.show.47"," matrixName":" literacy"," levelName":" null"," taskName":" null"," problemName":" BPOP_K_K-I-W"," problemNumber":" 8"," substepNumber":" 1"," substepProblem":" 1"," attemptNumber":" 1"," expectedAnswer":" K"," userResponse":" K"," correctness":" CORRECT"," feedbackType":" null"," totalProblemsCount":" 10"," promotionMode":" PROMOTION"," scaffolding":" null"}},
{"type":"LOG_DATA","tutor":"bpop.ltr.uc:K..K.all.rand.all.stat.show.47","class":"INFO","tag":"PERFORMANCE_TAG","time":"1548327875067","data":{"timestamp":" 1548327875066"," userId":" 5B12002999"," sessionId":" 5B12002999_20190124_140327"," gameId":" 0c16d53e-b4f7-4771-a5c1-4c31f0ce8671"," language":" LANG_SW"," tutorName":" bubble_pop"," tutorId":" bpop.ltr.uc_K..K.all.rand.all.stat.show.47"," matrixName":" literacy"," levelName":" null"," taskName":" null"," problemName":" BPOP_K_V-K-F"," problemNumber":" 9"," substepNumber":" 1"," substepProblem":" 1"," attemptNumber":" 1"," expectedAnswer":" K"," userResponse":" K"," correctness":" CORRECT"," feedbackType":" null"," totalProblemsCount":" 10"," promotionMode":" PROMOTION"," scaffolding":" null"}},
{"type":"LOG_DATA","tutor":"bpop.ltr.uc:K..K.all.rand.all.stat.show.47","class":"INFO","tag":"PERFORMANCE_TAG","time":"1548327879723","data":{"timestamp":" 1548327879723"," userId":" 5B12002999"," sessionId":" 5B12002999_20190124_140327"," gameId":" 0c16d53e-b4f7-4771-a5c1-4c31f0ce8671"," language":" LANG_SW"," tutorName":" bubble_pop"," tutorId":" bpop.ltr.uc_K..K.all.rand.all.stat.show.47"," matrixName":" literacy"," levelName":" null"," taskName":" null"," problemName":" BPOP_K_O-K-N"," problemNumber":" 10"," substepNumber":" 1"," substepProblem":" 1"," attemptNumber":" 1"," expectedAnswer":" K"," userResponse":" K"," correctness":" CORRECT"," feedbackType":" null"," totalProblemsCount":" 10"," promotionMode":" PROMOTION"," scaffolding":" null"}},
{"type":"LOG_DATA","tutor":"bpop.ltr.uc:K..K.all.rand.all.stat.show.47","class":"INFO","tag":"PERFORMANCE_TAG","time":"1548327885482","data":{"timestamp":" 1548327885482"," userId":" 5B12002999"," sessionId":" 5B12002999_20190124_140327"," gameId":" 0c16d53e-b4f7-4771-a5c1-4c31f0ce8671"," language":" LANG_SW"," tutorName":" bubble_pop"," tutorId":" bpop.ltr.uc_K..K.all.rand.all.stat.show.47"," matrixName":" literacy"," levelName":" null"," taskName":" ENDTUTOR"," problemName":" BPOP_K_O-K-N"," problemNumber":" 10"," substepNumber":" -1"," substepProblem":" 0"," attemptNumber":" 1"," expectedAnswer":" null"," userResponse":" null"," correctness":" null"," feedbackType":" null"," totalProblemsCount":" 0"," promotionMode":" PROMOTION"," scaffolding":" null"}},
{"type":"LOG_DATA","tutor":"bpop.ltr.uc:K..K.all.rand.all.stat.show.47","class":"INFO","tag":"PERFORMANCE_TAG","time":"1548327897086","data":{"timestamp":" 1548327897086"," userId":" 5B12002999"," sessionId":" 5B12002999_20190124_140327"," gameId":" 3b71e8e0-aea3-4ebd-bcb5-ffb68fe27140"," language":" LANG_SW"," tutorName":" bubble_pop"," tutorId":" bpop.ltr.uc_K..K.all.rand.all.stat.show.47"," matrixName":" literacy"," levelName":" null"," taskName":" null"," problemName":" BPOP_K_V-E-K"," problemNumber":" 1"," substepNumber":" 1"," substepProblem":" 1"," attemptNumber":" 1"," expectedAnswer":" K"," userResponse":" K"," correctness":" CORRECT"," feedbackType":" null"," totalProblemsCount":" 10"," promotionMode":" PROMOTION"," scaffolding":" null"}},
{"type":"LOG_DATA","tutor":"bpop.ltr.uc:K..K.all.rand.all.stat.show.47","class":"INFO","tag":"PERFORMANCE_TAG","time":"1548327900074","data":{"timestamp":" 1548327900074"," userId":" 5B12002999"," sessionId":" 5B12002999_20190124_140327"," gameId":" 3b71e8e0-aea3-4ebd-bcb5-ffb68fe27140"," language":" LANG_SW"," tutorName":" bubble_pop"," tutorId":" bpop.ltr.uc_K..K.all.rand.all.stat.show.47"," matrixName":" literacy"," levelName":" null"," taskName":" null"," problemName":" BPOP_K_J-K-R"," problemNumber":" 2"," substepNumber":" 1"," substepProblem":" 1"," attemptNumber":" 1"," expectedAnswer":" K"," userResponse":" K"," correctness":" CORRECT"," feedbackType":" null"," totalProblemsCount":" 10"," promotionMode":" PROMOTION"," scaffolding":" null"}},
{"type":"LOG_DATA","tutor":"bpop.ltr.uc:K..K.all.rand.all.stat.show.47","class":"INFO","tag":"PERFORMANCE_TAG","time":"1548327908343","data":{"timestamp":" 1548327908343"," userId":" 5B12002999"," sessionId":" 5B12002999_20190124_140327"," gameId":" 3b71e8e0-aea3-4ebd-bcb5-ffb68fe27140"," language":" LANG_SW"," tutorName":" bubble_pop"," tutorId":" bpop.ltr.uc_K..K.all.rand.all.stat.show.47"," matrixName":" literacy"," levelName":" null"," taskName":" null"," problemName":" BPOP_K_V-J-K"," problemNumber":" 3"," substepNumber":" 1"," substepProblem":" 1"," attemptNumber":" 1"," expectedAnswer":" K"," userResponse":" K"," correctness":" CORRECT"," feedbackType":" null"," totalProblemsCount":" 10"," promotionMode":" PROMOTION"," scaffolding":" null"}},
{"type":"LOG_DATA","tutor":"bpop.ltr.uc:K..K.all.rand.all.stat.show.47","class":"INFO","tag":"PERFORMANCE_TAG","time":"1548327924806","data":{"timestamp":" 1548327924805"," userId":" 5B12002999"," sessionId":" 5B12002999_20190124_140327"," gameId":" 3b71e8e0-aea3-4ebd-bcb5-ffb68fe27140"," language":" LANG_SW"," tutorName":" bubble_pop"," tutorId":" bpop.ltr.uc_K..K.all.rand.all.stat.show.47"," matrixName":" literacy"," levelName":" null"," taskName":" null"," problemName":" BPOP_K_K-I-W"," problemNumber":" 4"," substepNumber":" 1"," substepProblem":" 1"," attemptNumber":" 1"," expectedAnswer":" K"," userResponse":" K"," correctness":" CORRECT"," feedbackType":" null"," totalProblemsCount":" 10"," promotionMode":" PROMOTION"," scaffolding":" null"}},
{"type":"LOG_DATA","tutor":"bpop.ltr.uc:K..K.all.rand.all.stat.show.47","class":"INFO","tag":"PERFORMANCE_TAG","time":"1548327928170","data":{"timestamp":" 1548327928170"," userId":" 5B12002999"," sessionId":" 5B12002999_20190124_140327"," gameId":" 3b71e8e0-aea3-4ebd-bcb5-ffb68fe27140"," language":" LANG_SW"," tutorName":" bubble_pop"," tutorId":" bpop.ltr.uc_K..K.all.rand.all.stat.show.47"," matrixName":" literacy"," levelName":" null"," taskName":" null"," problemName":" BPOP_K_Z-K-O"," problemNumber":" 5"," substepNumber":" 1"," substepProblem":" 1"," attemptNumber":" 1"," expectedAnswer":" K"," userResponse":" K"," correctness":" CORRECT"," feedbackType":" null"," totalProblemsCount":" 10"," promotionMode":" PROMOTION"," scaffolding":" null"}},
{"type":"LOG_DATA","tutor":"bpop.ltr.uc:K..K.all.rand.all.stat.show.47","class":"INFO","tag":"PERFORMANCE_TAG","time":"1548327932504","data":{"timestamp":" 1548327932504"," userId":" 5B12002999"," sessionId":" 5B12002999_20190124_140327"," gameId":" 3b71e8e0-aea3-4ebd-bcb5-ffb68fe27140"," language":" LANG_SW"," tutorName":" bubble_pop"," tutorId":" bpop.ltr.uc_K..K.all.rand.all.stat.show.47"," matrixName":" literacy"," levelName":" null"," taskName":" null"," problemName":" BPOP_K_V-K-F"," problemNumber":" 6"," substepNumber":" 1"," substepProblem":" 1"," attemptNumber":" 1"," expectedAnswer":" K"," userResponse":" K"," correctness":" CORRECT"," feedbackType":" null"," totalProblemsCount":" 10"," promotionMode":" PROMOTION"," scaffolding":" null"}},
{"type":"LOG_DATA","tutor":"bpop.ltr.uc:K..K.all.rand.all.stat.show.47","class":"INFO","tag":"PERFORMANCE_TAG","time":"1548327937575","data":{"timestamp":" 1548327937575"," userId":" 5B12002999"," sessionId":" 5B12002999_20190124_140327"," gameId":" 3b71e8e0-aea3-4ebd-bcb5-ffb68fe27140"," language":" LANG_SW"," tutorName":" bubble_pop"," tutorId":" bpop.ltr.uc_K..K.all.rand.all.stat.show.47"," matrixName":" literacy"," levelName":" null"," taskName":" null"," problemName":" BPOP_K_J-Y-K"," problemNumber":" 7"," substepNumber":" 1"," substepProblem":" 1"," attemptNumber":" 1"," expectedAnswer":" K"," userResponse":" K"," correctness":" CORRECT"," feedbackType":" null"," totalProblemsCount":" 10"," promotionMode":" PROMOTION"," scaffolding":" null"}},
{"type":"LOG_DATA","tutor":"bpop.ltr.uc:K..K.all.rand.all.stat.show.47","class":"INFO","tag":"PERFORMANCE_TAG","time":"1548327949204","data":{"timestamp":" 1548327949204"," userId":" 5B12002999"," sessionId":" 5B12002999_20190124_140327"," gameId":" 3b71e8e0-aea3-4ebd-bcb5-ffb68fe27140"," language":" LANG_SW"," tutorName":" bubble_pop"," tutorId":" bpop.ltr.uc_K..K.all.rand.all.stat.show.47"," matrixName":" literacy"," levelName":" null"," taskName":" null"," problemName":" BPOP_K_O-K-N"," problemNumber":" 8"," substepNumber":" 1"," substepProblem":" 1"," attemptNumber":" 1"," expectedAnswer":" K"," userResponse":" K"," correctness":" CORRECT"," feedbackType":" null"," totalProblemsCount":" 10"," promotionMode":" PROMOTION"," scaffolding":" null"}},
{"type":"LOG_DATA","tutor":"bpop.ltr.uc:K..K.all.rand.all.stat.show.47","class":"INFO","tag":"PERFORMANCE_TAG","time":"1548327953666","data":{"timestamp":" 1548327953666"," userId":" 5B12002999"," sessionId":" 5B12002999_20190124_140327"," gameId":" 3b71e8e0-aea3-4ebd-bcb5-ffb68fe27140"," language":" LANG_SW"," tutorName":" bubble_pop"," tutorId":" bpop.ltr.uc_K..K.all.rand.all.stat.show.47"," matrixName":" literacy"," levelName":" null"," taskName":" null"," problemName":" BPOP_K_D-K-R"," problemNumber":" 9"," substepNumber":" 1"," substepProblem":" 1"," attemptNumber":" 1"," expectedAnswer":" K"," userResponse":" K"," correctness":" CORRECT"," feedbackType":" null"," totalProblemsCount":" 10"," promotionMode":" PROMOTION"," scaffolding":" null"}},
{"type":"LOG_DATA","tutor":"bpop.ltr.uc:K..K.all.rand.all.stat.show.47","class":"INFO","tag":"PERFORMANCE_TAG","time":"1548327962952","data":{"timestamp":" 1548327962952"," userId":" 5B12002999"," sessionId":" 5B12002999_20190124_140327"," gameId":" 3b71e8e0-aea3-4ebd-bcb5-ffb68fe27140"," language":" LANG_SW"," tutorName":" bubble_pop"," tutorId":" bpop.ltr.uc_K..K.all.rand.all.stat.show.47"," matrixName":" literacy"," levelName":" null"," taskName":" null"," problemName":" BPOP_K_K-V-CH"," problemNumber":" 10"," substepNumber":" 1"," substepProblem":" 1"," attemptNumber":" 1"," expectedAnswer":" K"," userResponse":" K"," correctness":" CORRECT"," feedbackType":" null"," totalProblemsCount":" 10"," promotionMode":" PROMOTION"," scaffolding":" null"}},
{"type":"LOG_DATA","tutor":"bpop.ltr.uc:K..K.all.rand.all.stat.show.47","class":"INFO","tag":"PERFORMANCE_TAG","time":"1548327968698","data":{"timestamp":" 1548327968697"," userId":" 5B12002999"," sessionId":" 5B12002999_20190124_140327"," gameId":" 3b71e8e0-aea3-4ebd-bcb5-ffb68fe27140"," language":" LANG_SW"," tutorName":" bubble_pop"," tutorId":" bpop.ltr.uc_K..K.all.rand.all.stat.show.47"," matrixName":" literacy"," levelName":" null"," taskName":" ENDTUTOR"," problemName":" BPOP_K_K-V-CH"," problemNumber":" 10"," substepNumber":" -1"," substepProblem":" 0"," attemptNumber":" 1"," expectedAnswer":" null"," userResponse":" null"," correctness":" null"," feedbackType":" null"," totalProblemsCount":" 0"," promotionMode":" PROMOTION"," scaffolding":" null"}},
{"type":"LOG_DATA","tutor":"bpop.ltr.uc:K..K.all.rand.all.stat.show.47","class":"INFO","tag":"PERFORMANCE_TAG","time":"1548327981322","data":{"timestamp":" 1548327981322"," userId":" 5B12002999"," sessionId":" 5B12002999_20190124_140327"," gameId":" 8bb803fc-9b93-4db2-82f8-16e3653f8989"," language":" LANG_SW"," tutorName":" bubble_pop"," tutorId":" bpop.ltr.uc_K..K.all.rand.all.stat.show.47"," matrixName":" literacy"," levelName":" null"," taskName":" null"," problemName":" BPOP_K_J-Y-K"," problemNumber":" 1"," substepNumber":" 1"," substepProblem":" 1"," attemptNumber":" 1"," expectedAnswer":" K"," userResponse":" K"," correctness":" CORRECT"," feedbackType":" null"," totalProblemsCount":" 10"," promotionMode":" PROMOTION"," scaffolding":" null"}},
{"type":"LOG_DATA","tutor":"bpop.ltr.uc:K..K.all.rand.all.stat.show.47","class":"INFO","tag":"PERFORMANCE_TAG","time":"1548327984867","data":{"timestamp":" 1548327984867"," userId":" 5B12002999"," sessionId":" 5B12002999_20190124_140327"," gameId":" 8bb803fc-9b93-4db2-82f8-16e3653f8989"," language":" LANG_SW"," tutorName":" bubble_pop"," tutorId":" bpop.ltr.uc_K..K.all.rand.all.stat.show.47"," matrixName":" literacy"," levelName":" null"," taskName":" null"," problemName":" BPOP_K_Z-K-O"," problemNumber":" 2"," substepNumber":" 1"," substepProblem":" 1"," attemptNumber":" 1"," expectedAnswer":" K"," userResponse":" K"," correctness":" CORRECT"," feedbackType":" null"," totalProblemsCount":" 10"," promotionMode":" PROMOTION"," scaffolding":" null"}},
{"type":"LOG_DATA","tutor":"bpop.ltr.uc:K..K.all.rand.all.stat.show.47","class":"INFO","tag":"PERFORMANCE_TAG","time":"1548327999446","data":{"timestamp":" 1548327999446"," userId":" 5B12002999"," sessionId":" 5B12002999_20190124_140327"," gameId":" 8bb803fc-9b93-4db2-82f8-16e3653f8989"," language":" LANG_SW"," tutorName":" bubble_pop"," tutorId":" bpop.ltr.uc_K..K.all.rand.all.stat.show.47"," matrixName":" literacy"," levelName":" null"," taskName":" null"," problemName":" BPOP_K_K-V-CH"," problemNumber":" 3"," substepNumber":" 1"," substepProblem":" 1"," attemptNumber":" 1"," expectedAnswer":" K"," userResponse":" K"," correctness":" CORRECT"," feedbackType":" null"," totalProblemsCount":" 10"," promotionMode":" PROMOTION"," scaffolding":" null"}},
{"type":"LOG_DATA","tutor":"bpop.ltr.uc:K..K.all.rand.all.stat.show.47","class":"INFO","tag":"PERFORMANCE_TAG","time":"1548328002706","data":{"timestamp":" 1548328002706"," userId":" 5B12002999"," sessionId":" 5B12002999_20190124_140327"," gameId":" 8bb803fc-9b93-4db2-82f8-16e3653f8989"," language":" LANG_SW"," tutorName":" bubble_pop"," tutorId":" bpop.ltr.uc_K..K.all.rand.all.stat.show.47"," matrixName":" literacy"," levelName":" null"," taskName":" null"," problemName":" BPOP_K_D-K-R"," problemNumber":" 4"," substepNumber":" 1"," substepProblem":" 1"," attemptNumber":" 1"," expectedAnswer":" K"," userResponse":" K"," correctness":" CORRECT"," feedbackType":" null"," totalProblemsCount":" 10"," promotionMode":" PROMOTION"," scaffolding":" null"}},
{"type":"LOG_DATA","tutor":"bpop.ltr.uc:K..K.all.rand.all.stat.show.47","class":"INFO","tag":"PERFORMANCE_TAG","time":"1548328016554","data":{"timestamp":" 1548328016554"," userId":" 5B12002999"," sessionId":" 5B12002999_20190124_140327"," gameId":" 8bb803fc-9b93-4db2-82f8-16e3653f8989"," language":" LANG_SW"," tutorName":" bubble_pop"," tutorId":" bpop.ltr.uc_K..K.all.rand.all.stat.show.47"," matrixName":" literacy"," levelName":" null"," taskName":" null"," problemName":" BPOP_K_O-K-N"," problemNumber":" 5"," substepNumber":" 1"," substepProblem":" 1"," attemptNumber":" 1"," expectedAnswer":" K"," userResponse":" K"," correctness":" CORRECT"," feedbackType":" null"," totalProblemsCount":" 10"," promotionMode":" PROMOTION"," scaffolding":" null"}},
{"type":"LOG_DATA","tutor":"bpop.ltr.uc:K..K.all.rand.all.stat.show.47","class":"INFO","tag":"PERFORMANCE_TAG","time":"1548328027916","data":{"timestamp":" 1548328027916"," userId":" 5B12002999"," sessionId":" 5B12002999_20190124_140327"," gameId":" 8bb803fc-9b93-4db2-82f8-16e3653f8989"," language":" LANG_SW"," tutorName":" bubble_pop"," tutorId":" bpop.ltr.uc_K..K.all.rand.all.stat.show.47"," matrixName":" literacy"," levelName":" null"," taskName":" null"," problemName":" BPOP_K_V-E-K"," problemNumber":" 6"," substepNumber":" 1"," substepProblem":" 1"," attemptNumber":" 1"," expectedAnswer":" K"," userResponse":" K"," correctness":" CORRECT"," feedbackType":" null"," totalProblemsCount":" 10"," promotionMode":" PROMOTION"," scaffolding":" null"}},
{"type":"LOG_DATA","tutor":"bpop.ltr.uc:K..K.all.rand.all.stat.show.47","class":"INFO","tag":"PERFORMANCE_TAG","time":"1548328031573","data":{"timestamp":" 1548328031572"," userId":" 5B12002999"," sessionId":" 5B12002999_20190124_140327"," gameId":" 8bb803fc-9b93-4db2-82f8-16e3653f8989"," language":" LANG_SW"," tutorName":" bubble_pop"," tutorId":" bpop.ltr.uc_K..K.all.rand.all.stat.show.47"," matrixName":" literacy"," levelName":" null"," taskName":" null"," problemName":" BPOP_K_J-K-R"," problemNumber":" 7"," substepNumber":" 1"," substepProblem":" 1"," attemptNumber":" 1"," expectedAnswer":" K"," userResponse":" K"," correctness":" CORRECT"," feedbackType":" null"," totalProblemsCount":" 10"," promotionMode":" PROMOTION"," scaffolding":" null"}},
{"type":"LOG_DATA","tutor":"bpop.ltr.uc:K..K.all.rand.all.stat.show.47","class":"INFO","tag":"PERFORMANCE_TAG","time":"1548328043801","data":{"timestamp":" 1548328043801"," userId":" 5B12002999"," sessionId":" 5B12002999_20190124_140327"," gameId":" 8bb803fc-9b93-4db2-82f8-16e3653f8989"," language":" LANG_SW"," tutorName":" bubble_pop"," tutorId":" bpop.ltr.uc_K..K.all.rand.all.stat.show.47"," matrixName":" literacy"," levelName":" null"," taskName":" null"," problemName":" BPOP_K_V-K-F"," problemNumber":" 8"," substepNumber":" 1"," substepProblem":" 1"," attemptNumber":" 1"," expectedAnswer":" K"," userResponse":" K"," correctness":" CORRECT"," feedbackType":" null"," totalProblemsCount":" 10"," promotionMode":" PROMOTION"," scaffolding":" null"}},
{"type":"LOG_DATA","tutor":"bpop.ltr.uc:K..K.all.rand.all.stat.show.47","class":"INFO","tag":"PERFORMANCE_TAG","time":"1548328055223","data":{"timestamp":" 1548328055223"," userId":" 5B12002999"," sessionId":" 5B12002999_20190124_140327"," gameId":" 8bb803fc-9b93-4db2-82f8-16e3653f8989"," language":" LANG_SW"," tutorName":" bubble_pop"," tutorId":" bpop.ltr.uc_K..K.all.rand.all.stat.show.47"," matrixName":" literacy"," levelName":" null"," taskName":" null"," problemName":" BPOP_K_V-J-K"," problemNumber":" 9"," substepNumber":" 1"," substepProblem":" 1"," attemptNumber":" 1"," expectedAnswer":" K"," userResponse":" K"," correctness":" CORRECT"," feedbackType":" null"," totalProblemsCount":" 10"," promotionMode":" PROMOTION"," scaffolding":" null"}},
{"type":"LOG_DATA","tutor":"bpop.ltr.uc:K..K.all.rand.all.stat.show.47","class":"INFO","tag":"PERFORMANCE_TAG","time":"1548328063060","data":{"timestamp":" 1548328063060"," userId":" 5B12002999"," sessionId":" 5B12002999_20190124_140327"," gameId":" 8bb803fc-9b93-4db2-82f8-16e3653f8989"," language":" LANG_SW"," tutorName":" bubble_pop"," tutorId":" bpop.ltr.uc_K..K.all.rand.all.stat.show.47"," matrixName":" literacy"," levelName":" null"," taskName":" null"," problemName":" BPOP_K_K-I-W"," problemNumber":" 10"," substepNumber":" 1"," substepProblem":" 1"," attemptNumber":" 1"," expectedAnswer":" K"," userResponse":" K"," correctness":" CORRECT"," feedbackType":" null"," totalProblemsCount":" 10"," promotionMode":" PROMOTION"," scaffolding":" null"}},
{"type":"LOG_DATA","tutor":"bpop.ltr.uc:K..K.all.rand.all.stat.show.47","class":"INFO","tag":"PERFORMANCE_TAG","time":"1548328068825","data":{"timestamp":" 1548328068825"," userId":" 5B12002999"," sessionId":" 5B12002999_20190124_140327"," gameId":" 8bb803fc-9b93-4db2-82f8-16e3653f8989"," language":" LANG_SW"," tutorName":" bubble_pop"," tutorId":" bpop.ltr.uc_K..K.all.rand.all.stat.show.47"," matrixName":" literacy"," levelName":" null"," taskName":" ENDTUTOR"," problemName":" BPOP_K_K-I-W"," problemNumber":" 10"," substepNumber":" -1"," substepProblem":" 0"," attemptNumber":" 1"," expectedAnswer":" null"," userResponse":" null"," correctness":" null"," feedbackType":" null"," totalProblemsCount":" 0"," promotionMode":" PROMOTION"," scaffolding":" null"}},
{"end":"end"}]}