{"947983430554":{"type":"bo","bookName":"Lesson%203","subjectName":"Hatua%203","fName":"users/MS0vYW5kcm9pZF9hc3NldC93d3cvc2Nob29sL1Vzb21hamklMjBuYSUyMFVhbmRpc2hpL0hhdHVhJTIwMy9MZXNzb24lMjAzL2luZGV4Lmh0bWwtYW5hbHl0aWNzLTk0Nzk4MzQzMDUxOA==.json"},"947983430564":{"type":"bo","bookName":"Lesson%203","subjectName":"Hatua%203","fName":"users/MS0vYW5kcm9pZF9hc3NldC93d3cvc2Nob29sL1Vzb21hamklMjBuYSUyMFVhbmRpc2hpL0hhdHVhJTIwMy9MZXNzb24lMjAzL2luZGV4Lmh0bWwtYW5hbHl0aWNzLTk0Nzk4MzQzMDUxOA==.json"},"947983430646":{"type":"xl"},"947983430982":{"type":"xp","pageCount":16},"947983431237":{"type":"fl"},"947983431275":{"type":"st","linkname":"Page"},"947983431280":{"type":"ss","linkname":"Page"},"947983454117":{"type":"ut","page":1,"pt":{"x":14,"y":326}},"947983462660":{"type":"sf","linkname":"Page"},"947983572474":{"type":"ut","page":1,"pt":{"x":54,"y":746}},"947983572583":{"type":"lt","linkname":"audio button"},"947983572584":{"type":"st","linkname":"audio button"},"947983572587":{"type":"ss","linkname":"audio button"},"947983590208":{"type":"sf","linkname":"audio button"},"947983782283":{"type":"ut","page":1,"pt":{"x":741,"y":794}},"947983800383":{"type":"ut","page":1,"pt":{"x":411,"y":787}},"947983804306":{"type":"ut","page":1,"pt":{"x":487,"y":819}},"947983817351":{"type":"ut","page":1,"pt":{"x":423,"y":803}},"947983823037":{"type":"ut","page":1,"pt":{"x":324,"y":661}},"947983823073":{"type":"ut","page":1,"pt":{"x":327,"y":635}},"947983831980":{"type":"ut","page":1,"pt":{"x":0,"y":795}},"947983833013":{"type":"ut","page":1,"pt":{"x":0,"y":750}},"947983833189":{"type":"lt","linkname":"audio button"},"947983833190":{"type":"st","linkname":"audio button"},"947983833191":{"type":"ss","linkname":"audio button"},"947983850787":{"type":"sf","linkname":"audio button"},"947983883713":{"type":"ut","page":1,"pt":{"x":489,"y":663}},"947983883796":{"type":"ut","page":1,"pt":{"x":423,"y":675}},"947983883863":{"type":"ut","page":1,"pt":{"x":378,"y":674}},"947983886342":{"type":"ut","page":1,"pt":{"x":806,"y":723}},"947983886373":{"type":"ut","page":1,"pt":{"x":825,"y":546}},"947983886386":{"type":"ut","page":1,"pt":{"x":831,"y":743}},"947983886390":{"type":"ut","page":1,"pt":{"x":831,"y":743}},"947983886642":{"type":"ut","page":1,"pt":{"x":675,"y":40}},"947983887584":{"type":"ut","page":1,"pt":{"x":545,"y":76}},"947983887652":{"type":"ut","page":1,"pt":{"x":623,"y":215}},"947983887671":{"type":"ut","page":1,"pt":{"x":544,"y":71}},"947983887701":{"type":"ut","page":1,"pt":{"x":535,"y":49}},"947983887747":{"type":"ut","page":1,"pt":{"x":613,"y":111}},"947983888167":{"type":"ut","page":1,"pt":{"x":559,"y":331}},"947983888178":{"type":"ut","page":1,"pt":{"x":693,"y":357}},"947983888236":{"type":"ut","page":1,"pt":{"x":437,"y":76}},"947983888257":{"type":"ut","page":1,"pt":{"x":713,"y":393}},"947983891800":{"type":"ut","page":1,"pt":{"x":1013,"y":779}},"947983891821":{"type":"ut","page":1,"pt":{"x":1012,"y":778}},"947983891853":{"type":"ut","page":1,"pt":{"x":1011,"y":778}},"947983891929":{"type":"ut","page":1,"pt":{"x":1010,"y":779}},"947983892036":{"type":"ut","page":1,"pt":{"x":1009,"y":779}},"947983892113":{"type":"ut","page":1,"pt":{"x":1009,"y":778}},"947983892401":{"type":"ut","page":1,"pt":{"x":1003,"y":778}},"947983892500":{"type":"ut","page":1,"pt":{"x":1002,"y":778}},"947983893153":{"type":"ut","page":1,"pt":{"x":974,"y":788}},"947983893740":{"type":"ut","page":1,"pt":{"x":980,"y":779}},"947983894323":{"type":"ut","page":1,"pt":{"x":980,"y":784}},"947983894445":{"type":"ut","page":1,"pt":{"x":978,"y":781}},"947983894635":{"type":"ut","page":1,"pt":{"x":976,"y":782}},"947983894835":{"type":"ut","page":1,"pt":{"x":972,"y":783}},"947983896436":{"type":"ut","page":1,"pt":{"x":639,"y":351}},"947983896629":{"type":"ut","page":1,"pt":{"x":451,"y":731}},"947983897230":{"type":"ut","page":1,"pt":{"x":398,"y":753}},"947983897294":{"type":"ut","page":1,"pt":{"x":406,"y":749}},"947983897482":{"type":"ut","page":1,"pt":{"x":407,"y":745}},"947983897656":{"type":"ut","page":1,"pt":{"x":440,"y":726}},"947983897776":{"type":"ut","page":1,"pt":{"x":436,"y":732}},"947983897837":{"type":"ut","page":1,"pt":{"x":433,"y":736}},"947983897876":{"type":"ut","page":1,"pt":{"x":433,"y":736}},"947983898035":{"type":"ut","page":1,"pt":{"x":440,"y":727}},"947983898074":{"type":"ut","page":1,"pt":{"x":443,"y":724}},"947983898093":{"type":"ut","page":1,"pt":{"x":444,"y":723}},"947983898115":{"type":"ut","page":1,"pt":{"x":444,"y":721}},"947983898134":{"type":"ut","page":1,"pt":{"x":444,"y":720}},"947983898207":{"type":"ut","page":1,"pt":{"x":442,"y":722}},"947983898286":{"type":"ut","page":1,"pt":{"x":437,"y":725}},"947983898328":{"type":"ut","page":1,"pt":{"x":436,"y":727}},"947983898383":{"type":"ut","page":1,"pt":{"x":435,"y":728}},"947983898411":{"type":"ut","page":1,"pt":{"x":435,"y":729}},"947983898440":{"type":"ut","page":1,"pt":{"x":435,"y":729}},"947983898479":{"type":"ut","page":1,"pt":{"x":436,"y":729}},"947983898860":{"type":"ut","page":1,"pt":{"x":454,"y":695}},"947983936122":{"type":"ut","page":1,"pt":{"x":1246,"y":775}},"947983936747":{"type":"lt","linkname":"next page button"},"947983936748":{"type":"st","linkname":"next page button"},"947983936750":{"type":"ss","linkname":"next page button"},"947983936753":{"type":"sf","linkname":"next page button"},"947983936763":{"type":"sf","linkname":"next page button"},"947983937162":{"type":"pt","page":2},"947983937175":{"type":"st","linkname":"Page"},"947983937178":{"type":"ss","linkname":"Page"},"947983966480":{"type":"sf","linkname":"Page"},"947983987516":{"type":"ut","page":2,"pt":{"x":218,"y":558}},"947983987555":{"type":"lt","linkname":"ANSWER 02"},"947983987557":{"type":"st","linkname":"ANSWER 02"},"947983987568":{"type":"ss","linkname":"ANSWER 02"},"947983988951":{"type":"ut","page":2,"pt":{"x":440,"y":682}},"947983989265":{"type":"ut","page":2,"pt":{"x":473,"y":717}},"947983989841":{"type":"ut","page":2,"pt":{"x":471,"y":721}},"947983990000":{"type":"sf","linkname":"ANSWER 02"},"947983990275":{"type":"ut","page":2,"pt":{"x":421,"y":705}},"947983990374":{"type":"lt","linkname":"ANSWER 03 CORRECT"},"947983990376":{"type":"st","linkname":"ANSWER 03 CORRECT"},"947983990380":{"type":"ss","linkname":"ANSWER 03 CORRECT"},"947983990650":{"type":"ut","page":2,"pt":{"x":404,"y":707}},"947983993542":{"type":"sf","linkname":"ANSWER 03 CORRECT"},"947984068566":{"type":"ut","page":2,"pt":{"x":1207,"y":768}},"947984068655":{"type":"lt","linkname":"NEXT PAGE"},"947984068656":{"type":"st","linkname":"NEXT PAGE"},"947984068658":{"type":"ss","linkname":"NEXT PAGE"},"947984068659":{"type":"sf","linkname":"NEXT PAGE"},"947984068667":{"type":"sf","linkname":"NEXT PAGE"},"947984069066":{"type":"pt","page":3},"947984069086":{"type":"st","linkname":"Page"},"947984069091":{"type":"ss","linkname":"Page"},"947984095309":{"type":"sf","linkname":"Page"},"947984101277":{"type":"ut","page":3,"pt":{"x":1228,"y":173}},"947984101349":{"type":"lt","linkname":"check button 01"},"947984101351":{"type":"st","linkname":"check button 01"},"947984101364":{"type":"ss","linkname":"check button 01"},"947984105232":{"type":"sf","linkname":"check button 01"},"947984106193":{"type":"ut","page":3,"pt":{"x":1227,"y":719}},"947984106300":{"type":"lt","linkname":"next page"},"947984106301":{"type":"st","linkname":"next page"},"947984106303":{"type":"ss","linkname":"next page"},"947984106304":{"type":"sf","linkname":"next page"},"947984106311":{"type":"sf","linkname":"next page"},"947984106740":{"type":"pt","page":4},"947984106760":{"type":"st","linkname":"Page"},"947984106764":{"type":"ss","linkname":"Page"},"947984110056":{"type":"ut","page":4,"pt":{"x":1271,"y":586}},"947984111472":{"type":"ut","page":4,"pt":{"x":1222,"y":496}},"947984118610":{"type":"ut","page":4,"pt":{"x":1177,"y":680}},"947984138389":{"type":"sf","linkname":"Page"},"947984139709":{"type":"ut","page":4,"pt":{"x":73,"y":760}},"947984139799":{"type":"lt","linkname":"audio button"},"947984139801":{"type":"st","linkname":"audio button"},"947984139808":{"type":"ss","linkname":"audio button"},"947984158261":{"type":"sf","linkname":"audio button"},"947984159126":{"type":"ut","page":4,"pt":{"x":74,"y":751}},"947984159215":{"type":"lt","linkname":"audio button"},"947984159218":{"type":"st","linkname":"audio button"},"947984159220":{"type":"ss","linkname":"audio button"},"947984177612":{"type":"sf","linkname":"audio button"},"947984543059":{"type":"ut","page":4,"pt":{"x":61,"y":762}},"947984543082":{"type":"lt","linkname":"audio button"},"947984543084":{"type":"st","linkname":"audio button"},"947984543085":{"type":"ss","linkname":"audio button"},"947984559204":{"type":"ut","page":4,"pt":{"x":852,"y":798}},"947984559609":{"type":"ut","page":4,"pt":{"x":867,"y":781}},"947984561526":{"type":"sf","linkname":"audio button"},"947984562414":{"type":"ut","page":4,"pt":{"x":1197,"y":783}},"947984562519":{"type":"lt","linkname":"next page button"},"947984562520":{"type":"st","linkname":"next page button"},"947984562522":{"type":"ss","linkname":"next page button"},"947984562524":{"type":"sf","linkname":"next page button"},"947984562531":{"type":"sf","linkname":"next page button"},"947984562930":{"type":"pt","page":5},"947984562946":{"type":"st","linkname":"Page"},"947984562948":{"type":"ss","linkname":"Page"},"947984564771":{"type":"ut","page":5,"pt":{"x":1217,"y":488}},"947984564804":{"type":"ut","page":5,"pt":{"x":1217,"y":488}},"947984587409":{"type":"sf","linkname":"Page"},"947984722718":{"type":"ut","page":5,"pt":{"x":344,"y":64}},"947984722764":{"type":"lt","linkname":"QUESTION"},"947984722765":{"type":"st","linkname":"QUESTION"},"947984722773":{"type":"ss","linkname":"QUESTION"},"947984725141":{"type":"ut","page":5,"pt":{"x":1190,"y":507}},"947984727477":{"type":"sf","linkname":"QUESTION"},"947984736288":{"type":"ut","page":5,"pt":{"x":232,"y":733}},"947984736342":{"type":"lt","linkname":"ANSWER 03"},"947984736344":{"type":"st","linkname":"ANSWER 03"},"947984736345":{"type":"ss","linkname":"ANSWER 03"},"947984737343":{"type":"ut","page":5,"pt":{"x":164,"y":561}},"947984737626":{"type":"ut","page":5,"pt":{"x":213,"y":574}},"947984737876":{"type":"ut","page":5,"pt":{"x":189,"y":547}},"947984738109":{"type":"ut","page":5,"pt":{"x":193,"y":537}},"947984738368":{"type":"ut","page":5,"pt":{"x":188,"y":550}},"947984738610":{"type":"ut","page":5,"pt":{"x":195,"y":576}},"947984738704":{"type":"sf","linkname":"ANSWER 03"},"947984738860":{"type":"ut","page":5,"pt":{"x":219,"y":574}},"947984738919":{"type":"lt","linkname":"ANSWER 02 CORRECT"},"947984738920":{"type":"st","linkname":"ANSWER 02 CORRECT"},"947984738922":{"type":"ss","linkname":"ANSWER 02 CORRECT"},"947984739085":{"type":"ut","page":5,"pt":{"x":219,"y":559}},"947984742088":{"type":"sf","linkname":"ANSWER 02 CORRECT"},"947984742288":{"type":"ut","page":5,"pt":{"x":1238,"y":784}},"947984742369":{"type":"lt","linkname":"NEXT PAGE"},"947984742370":{"type":"st","linkname":"NEXT PAGE"},"947984742372":{"type":"ss","linkname":"NEXT PAGE"},"947984742374":{"type":"sf","linkname":"NEXT PAGE"},"947984742379":{"type":"sf","linkname":"NEXT PAGE"},"947984742765":{"type":"pt","page":6},"947984742781":{"type":"st","linkname":"Page"},"947984742784":{"type":"ss","linkname":"Page"},"947984769846":{"type":"sf","linkname":"Page"},"947984773870":{"type":"ut","page":6,"pt":{"x":1254,"y":212}},"947984774200":{"type":"ut","page":6,"pt":{"x":1242,"y":190}},"947984774267":{"type":"lt","linkname":"check button 01"},"947984774268":{"type":"st","linkname":"check button 01"},"947984774270":{"type":"ss","linkname":"check button 01"},"947984778137":{"type":"sf","linkname":"check button 01"},"947984778709":{"type":"ut","page":6,"pt":{"x":1186,"y":736}},"947984778783":{"type":"lt","linkname":"next page"},"947984778785":{"type":"st","linkname":"next page"},"947984778787":{"type":"ss","linkname":"next page"},"947984778789":{"type":"sf","linkname":"next page"},"947984778795":{"type":"sf","linkname":"next page"},"947984779227":{"type":"pt","page":7},"947984779244":{"type":"st","linkname":"Page"},"947984779247":{"type":"ss","linkname":"Page"},"947984790250":{"type":"ut","page":7,"pt":{"x":1265,"y":663}},"947984807788":{"type":"sf","linkname":"Page"},"947985017628":{"type":"ut","page":7,"pt":{"x":839,"y":802}},"947985201406":{"type":"ut","page":7,"pt":{"x":69,"y":753}},"947985201412":{"type":"lt","linkname":"audio button"},"947985201415":{"type":"st","linkname":"audio button"},"947985201421":{"type":"ss","linkname":"audio button"},"947985206206":{"type":"ut","page":7,"pt":{"x":942,"y":207}},"947985206212":{"type":"ut","page":7,"pt":{"x":942,"y":207}},"947985206220":{"type":"ut","page":7,"pt":{"x":943,"y":203}},"947985206350":{"type":"ut","page":7,"pt":{"x":953,"y":135}},"947985206364":{"type":"ut","page":7,"pt":{"x":949,"y":132}},"947985206369":{"type":"ut","page":7,"pt":{"x":949,"y":132}},"947985206382":{"type":"ut","page":7,"pt":{"x":941,"y":128}},"947985206395":{"type":"ut","page":7,"pt":{"x":935,"y":125}},"947985206421":{"type":"ut","page":7,"pt":{"x":923,"y":121}},"947985206431":{"type":"ut","page":7,"pt":{"x":919,"y":119}},"947985206443":{"type":"ut","page":7,"pt":{"x":916,"y":119}},"947985206465":{"type":"ut","page":7,"pt":{"x":909,"y":117}},"947985206523":{"type":"ut","page":7,"pt":{"x":889,"y":109}},"947985206539":{"type":"ut","page":7,"pt":{"x":885,"y":108}},"947985206587":{"type":"ut","page":7,"pt":{"x":866,"y":98}},"947985206640":{"type":"ut","page":7,"pt":{"x":814,"y":75}},"947985206703":{"type":"ut","page":7,"pt":{"x":1137,"y":441}},"947985206716":{"type":"ut","page":7,"pt":{"x":1126,"y":435}},"947985206747":{"type":"ut","page":7,"pt":{"x":997,"y":363}},"947985206755":{"type":"ut","page":7,"pt":{"x":997,"y":363}},"947985206764":{"type":"ut","page":7,"pt":{"x":977,"y":354}},"947985206794":{"type":"ut","page":7,"pt":{"x":816,"y":282}},"947985206933":{"type":"ut","page":7,"pt":{"x":92,"y":122}},"947985208738":{"type":"ut","page":7,"pt":{"x":212,"y":476}},"947985208904":{"type":"ut","page":7,"pt":{"x":215,"y":393}},"947985208921":{"type":"ut","page":7,"pt":{"x":213,"y":378}},"947985209230":{"type":"ut","page":7,"pt":{"x":400,"y":174}},"947985209497":{"type":"ut","page":7,"pt":{"x":1247,"y":136}},"947985215710":{"type":"sf","linkname":"audio button"},"947985219202":{"type":"ut","page":7,"pt":{"x":73,"y":139}},"947985219376":{"type":"ut","page":7,"pt":{"x":101,"y":292}},"947985219475":{"type":"ut","page":7,"pt":{"x":140,"y":291}},"947985219546":{"type":"ut","page":7,"pt":{"x":160,"y":299}},"947985253158":{"type":"ut","page":7,"pt":{"x":46,"y":772}},"947985253190":{"type":"lt","linkname":"audio button"},"947985253192":{"type":"st","linkname":"audio button"},"947985253194":{"type":"ss","linkname":"audio button"}}